scraper/__init__.py
scraper/scraper.py
wkt_scraper-1.0.0.dist-info/LICENSE
wkt_scraper-1.0.0.dist-info/METADATA
wkt_scraper-1.0.0.dist-info/WHEEL
wkt_scraper-1.0.0.dist-info/top_level.txt
wkt_scraper-1.0.0.dist-info/RECORD
