Metadata-Version: 2.1
Name: wkt-scraper
Version: 1.0.0
Summary: Parse word information from Wiktionary
Home-page: https://github.com/fatih-akgul/wkt_scraper
Author: Fatih Akgul
Author-email: akguls@gmail.com
License: MIT
Keywords: wiktionary scraper parser
Platform: UNKNOWN
Classifier: License :: OSI Approved :: MIT License
Classifier: Programming Language :: Python :: 3
Classifier: Programming Language :: Python :: 3.7
Requires-Dist: bs4
Requires-Dist: requests
Requires-Dist: iso-639
